Metadata-Version: 2.1
Name: scrapy-incremental
Version: 0.1.1
Summary: The package uses Zyte's Collections API to keep a persistent state of previously scraped items between jobs, allowing the spiders to run in an incremental behavior, only returningnew items.
Home-page: UNKNOWN
License: UNKNOWN
Platform: UNKNOWN
License-File: LICENSE.txt
